noseblacklist/__init__.py
noseblacklist/plugin.py
nose_blacklist-0.0.2.dist-info/LICENSE
nose_blacklist-0.0.2.dist-info/METADATA
nose_blacklist-0.0.2.dist-info/WHEEL
nose_blacklist-0.0.2.dist-info/entry_points.txt
nose_blacklist-0.0.2.dist-info/top_level.txt
nose_blacklist-0.0.2.dist-info/RECORD
