Metadata-Version: 2.1
Name: nose-blacklist
Version: 0.0.2
Summary: test exclusion for nose with blacklists
Home-page: https://github.com/pglass/nose-blacklist
Author: Paul Glass
Author-email: pnglass@gmail.com
License: MIT
Keywords: nose blacklist skip exclude
Platform: UNKNOWN
Classifier: Development Status :: 3 - Alpha
Classifier: Environment :: Plugins
Classifier: Intended Audience :: Developers
Classifier: License :: OSI Approved :: MIT License
Classifier: Operating System :: OS Independent
Classifier: Programming Language :: Python :: 2.7
Classifier: Programming Language :: Python :: 3.6
Classifier: Programming Language :: Python :: 3.7
Classifier: Topic :: Software Development :: Testing
Requires-Dist: nose
Requires-Dist: six
